checkpasswords/__init__.py
checkpasswords/__main__.py
checkpasswords/auxiliary.py
checkpasswords/credentials.py
checkpasswords/io/__init__.py
checkpasswords/io/input.py
checkpasswords/io/output.py
checkpasswords/mfa_sites.txt
checkpasswords-2023.dist-info/entry_points.txt
checkpasswords-2023.dist-info/LICENSE.md
checkpasswords-2023.dist-info/METADATA
checkpasswords-2023.dist-info/WHEEL
checkpasswords-2023.dist-info/RECORD
