Metadata-Version: 2.1
Name: checkpasswords
Version: 2023
Summary: CheckPasswords uses pass_import to read a password manager source file to check for duplicate passwords; check for weak passwords; identify http sites; list available 2fa options; list emails
Home-page: https://github.com/FHPythonUtils/CheckPasswords
License: GPL-3.0-or-later
Author: FredHappyface
Requires-Python: >=3.8,<4.0
Classifier: Development Status :: 5 - Production/Stable
Classifier: Environment :: Console
Classifier: Environment :: MacOS X
Classifier: Environment :: Win32 (MS Windows)
Classifier: Intended Audience :: Developers
Classifier: Intended Audience :: Education
Classifier: License :: OSI Approved :: GNU General Public License v3 or later (GPLv3+)
Classifier: Natural Language :: English
Classifier: Operating System :: OS Independent
Classifier: Programming Language :: Python :: 3
Classifier: Programming Language :: Python :: 3.8
Classifier: Programming Language :: Python :: 3.9
Classifier: Programming Language :: Python :: 3.10
Classifier: Programming Language :: Python :: 3.11
Classifier: Programming Language :: Python :: Implementation :: CPython
Classifier: Topic :: Security
Classifier: Topic :: Software Development :: Libraries :: Python Modules
Classifier: Topic :: Utilities
Requires-Dist: pass-import (>=3.4,<4)
Requires-Dist: rich (>=13.4.2,<14)
Requires-Dist: zxcvbn-python (>=4.4.24,<5)
Project-URL: Documentation, https://github.com/FHPythonUtils/CheckPasswords/blob/master/README.md
Project-URL: Repository, https://github.com/FHPythonUtils/CheckPasswords
